MANIFEST.in
runtests.py
setup.py
django_twitterflux.egg-info/PKG-INFO
django_twitterflux.egg-info/SOURCES.txt
django_twitterflux.egg-info/dependency_links.txt
django_twitterflux.egg-info/not-zip-safe
django_twitterflux.egg-info/requires.txt
django_twitterflux.egg-info/top_level.txt
twitterflux/__init__.py
twitterflux/admin.py
twitterflux/models.py
twitterflux/settings.py
twitterflux/utils.py
twitterflux/management/__init__.py
twitterflux/management/commands/__init__.py
twitterflux/management/commands/retrieve_tweets.py
twitterflux/tests/__init__.py
twitterflux/tests/factories.py
twitterflux/tests/tests.py