Metadata-Version: 1.0
Name: django-twitterflux
Version: 0.0.3
Summary: Retrieval and storage of recent tweets in Django.
Home-page: https://github.com/sgarcez/django-twitter-flux/
Author: sergio Garcez
Author-email: garcez.sergio@gmail.com
License: BSD
Platform: UNKNOWN
Classifier: Development Status :: 3 - Alpha
Classifier: Intended Audience :: Developers
Classifier: Natural Language :: English
Classifier: Operating System :: OS Independent
Classifier: Framework :: Django
Classifier: Programming Language :: Python
